{
  "main": {
    "id": "38c84b586240ac80",
    "type": "split",
    "children": [
      {
        "id": "ad5701a1b2566afa",
        "type": "tabs",
        "children": [
          {
            "id": "b8d191262a3661cf",
            "type": "leaf",
            "state": {
              "type": "markdown",
              "state": {
                "file": "wiki/Function_Reference.md",
                "mode": "source",
                "source": false
              },
              "icon": "lucide-file",
              "title": "Function_Reference"
            }
          }
        ]
      }
    ],
    "direction": "vertical"
  },
  "left": {
    "id": "32ed0e29f0290c47",
    "type": "split",
    "children": [
      {
        "id": "c4c05124aa3d129a",
        "type": "tabs",
        "children": [
          {
            "id": "e72f329128ead12a",
            "type": "leaf",
            "state": {
              "type": "file-explorer",
              "state": {
                "sortOrder": "alphabetical",
                "autoReveal": false
              },
              "icon": "lucide-folder-closed",
              "title": "Explorador de archivos"
            }
          },
          {
            "id": "f0b1c92b7235e2f6",
            "type": "leaf",
            "state": {
              "type": "search",
              "state": {
                "query": "",
                "matchingCase": false,
                "explainSearch": false,
                "collapseAll": false,
                "extraContext": false,
                "sortOrder": "alphabetical"
              },
              "icon": "lucide-search",
              "title": "Buscar"
            }
          },
          {
            "id": "f0de8c79ce30c639",
            "type": "leaf",
            "state": {
              "type": "bookmarks",
              "state": {},
              "icon": "lucide-bookmark",
              "title": "Marcadores"
            }
          }
        ]
      }
    ],
    "direction": "horizontal",
    "width": 300
  },
  "right": {
    "id": "70d80ec766bb9057",
    "type": "split",
    "children": [
      {
        "id": "a518c124553f13c0",
        "type": "tabs",
        "children": [
          {
            "id": "b5b61fbe81e355cb",
            "type": "leaf",
            "state": {
              "type": "backlink",
              "state": {
                "file": "Bienvenido.md",
                "collapseAll": false,
                "extraContext": false,
                "sortOrder": "alphabetical",
                "showSearch": false,
                "searchQuery": "",
                "backlinkCollapsed": false,
                "unlinkedCollapsed": true
              },
              "icon": "links-coming-in",
              "title": "Enlaces entrantes de Bienvenido"
            }
          },
          {
            "id": "33d3b81256934921",
            "type": "leaf",
            "state": {
              "type": "outgoing-link",
              "state": {
                "file": "Bienvenido.md",
                "linksCollapsed": false,
                "unlinkedCollapsed": true
              },
              "icon": "links-going-out",
              "title": "Enlaces salientes de Bienvenido"
            }
          },
          {
            "id": "60bfd8b3e2f7b0af",
            "type": "leaf",
            "state": {
              "type": "tag",
              "state": {
                "sortOrder": "frequency",
                "useHierarchy": true,
                "showSearch": false,
                "searchQuery": ""
              },
              "icon": "lucide-tags",
              "title": "Etiquetas"
            }
          },
          {
            "id": "a48d01c0d036c4ff",
            "type": "leaf",
            "state": {
              "type": "all-properties",
              "state": {
                "sortOrder": "frequency",
                "showSearch": false,
                "searchQuery": ""
              },
              "icon": "lucide-archive",
              "title": "Todas las propiedades"
            }
          },
          {
            "id": "e3c604179f5fe55e",
            "type": "leaf",
            "state": {
              "type": "outline",
              "state": {
                "file": "Bienvenido.md",
                "followCursor": false,
                "showSearch": false,
                "searchQuery": ""
              },
              "icon": "lucide-list",
              "title": "Esquema de Bienvenido"
            }
          }
        ]
      }
    ],
    "direction": "horizontal",
    "width": 300,
    "collapsed": true
  },
  "left-ribbon": {
    "hiddenItems": {
      "switcher:Abrir selector rápido": false,
      "graph:Abrir vista gráfica": false,
      "canvas:Crear nuevo lienzo": false,
      "daily-notes:Abrir la nota de hoy": false,
      "templates:Insertar plantilla": false,
      "command-palette:Abrir paleta de comandos": false,
      "bases:Crear nueva base": false
    }
  },
  "active": "b8d191262a3661cf",
  "lastOpenFiles": [
    "wiki/Project_Conventions.md",
    "Team_Jhon_Guitarra.md",
    "Source_ANEXO_2_FORMATO_PERFIL_GUITARRA_JHON_v2.1.md",
    "wiki/Technical_Architecture.md",
    "wiki/DSP_Implementation.md",
    "raw/documentacion_completa_bb60c.md",
    "wiki/SDR_Hardware_Interface.md",
    "wiki/Function_Reference.md",
    "Bienvenido.md",
    "wiki/log.md",
    "wiki/index.md",
    "wiki/Project_Objectives.md",
    "desktop.ini"
  ]
}